HTMLReader/Element.py
HTMLReader/Read.py
HTMLReader/__init__.py
HTMLReader/strUtils.py
HTML_Reader-1.1.1.dist-info/LICENSE
HTML_Reader-1.1.1.dist-info/METADATA
HTML_Reader-1.1.1.dist-info/WHEEL
HTML_Reader-1.1.1.dist-info/top_level.txt
HTML_Reader-1.1.1.dist-info/RECORD
