Metadata-Version: 2.1
Name: HTML-Reader
Version: 1.1.1
Summary: Read HTML data and convert it into python classes.
Home-page: UNKNOWN
Author: Monkvy
Author-email: moluecke@gmx.de
License: UNKNOWN
Keywords: python,html,parser,reader
Platform: UNKNOWN
Classifier: Intended Audience :: Developers
Classifier: Programming Language :: Python :: 3
Classifier: Operating System :: Unix
Classifier: Operating System :: MacOS :: MacOS X
Classifier: Operating System :: Microsoft :: Windows
License-File: LICENSE
